{
  "start": {
    "make_menu": "🔝 Главное Меню",
    "referal": "ℹ️ Пользователь присоединился к боту по вашей ссылке.\n\nВсего рефералов: "
  },
  "menu": {
    "main": "ТУТ ГЛАВНОЕ МЕНЮ СЮДА ПОПАДАЮТ ПРИ НАЖАТИИ СТАРТ",
    "balance": {
      "balance": "Баланс: ",
      "referals": "\nКоличество рефералов: ",
      "text": "\n1 ref. = 777\n\nЧтобы получить больше монет приглашайте друзей"
    },
    "wallet": {
      "address": "Ваш кошелек\n",
      "text": "\n\nВам надо привязать свой кошелек и потом мы вам че нибкдь скинем"
    }
  },
  "main_button": {
    "balance": "💰 Баланс",
    "walet": "👛 Кошелек",
    "main": "🗒 Главная"
  },
  "subscribe": "Ошибочка! Надо сначала подписаться на канал: https://t.me/+KSKrzP7aIksyNDcy",
  "invite_friend": "Пригласить друга",
  "check_subscribe": {
    "check": "Я подписался",
    "not_subscribe": "Не обманывай, ты не подписался"
  },
  "scenes": {
    "stop": "🚫 Отмена",
    "wallet": {
      "input_adress": "Введите адрес кошелька:",
      "adress_complite": {
        "adress": "Адрес кошелька теперь: ",
        "text": "\nМы позже отправим токены\n\nЕсли вы ввели неправильно адрес кошелька, или же хотите его сменить, просто перейдите снова во вкладку 👛 Кошелек"
      }
    },
    "admin": {}
  }
}
